{"_invocation_id": "f0565bbf-d464-498e-a067-d6fdefc8b7e4", "linked": {"0": {"name": "source.project.fitness_tracker.customers", "type": "source", "succ": [9]}, "1": {"name": "source.project.fitness_tracker.products", "type": "source", "succ": [7]}, "2": {"name": "source.project.fitness_tracker.transaction", "type": "source", "succ": [4]}, "3": {"name": "model.project.kpi1", "type": "model"}, "4": {"name": "model.project.stg_transactions", "type": "model", "succ": [3, 5, 6, 8, 12, 14]}, "5": {"name": "model.project.kpi5", "type": "model"}, "6": {"name": "model.project.kpi6", "type": "model"}, "7": {"name": "model.project.stg_products", "type": "model", "succ": [6, 12]}, "8": {"name": "model.project.kpi7", "type": "model"}, "9": {"name": "model.project.stg_customers", "type": "model", "succ": [8, 12]}, "10": {"name": "seed.project.country_region", "type": "seed"}, "11": {"name": "model.project.kpi3", "type": "model"}, "12": {"name": "model.project.all_data", "type": "model", "succ": [13]}, "13": {"name": "model.project.kpi2", "type": "model"}, "14": {"name": "model.project.kpi4", "type": "model"}}}